zip_cen_op/__init__.py
zip_cen_op/main.py
zip_cen_op-0.1.1.dist-info/METADATA
zip_cen_op-0.1.1.dist-info/WHEEL
zip_cen_op-0.1.1.dist-info/entry_points.txt
zip_cen_op-0.1.1.dist-info/licenses/LICENSE
zip_cen_op-0.1.1.dist-info/RECORD
