Metadata-Version: 2.3
Name: zip-cen-op
Version: 0.1.1
Summary: A tool to manipulate ZIP file Central Directory encryption flags
Project-URL: Homepage, https://github.com/c9n/zip-cen-op
Project-URL: Bug Tracker, https://github.com/c9n/zip-cen-op/issues
Author-email: chen <chen@wepe.dev>
License-File: LICENSE
Classifier: License :: OSI Approved :: MIT License
Classifier: Operating System :: OS Independent
Classifier: Programming Language :: Python :: 3
Requires-Python: >=3.6
